fdbm
