Metadata-Version: 2.1
Name: fdbm
Version: 0.0.3
Summary: File data base system used to save/update/delete/find class objects to files easly
Home-page: https://github.com/IbrahimABBAS85/fdb
Author: Ibrahim Abbas
Author-email: i.abbas85@gmail.com
License: UNKNOWN
Platform: UNKNOWN
Classifier: Programming Language :: Python :: 3
Classifier: License :: OSI Approved :: MIT License
Classifier: Operating System :: OS Independent
Requires-Python: >=3.6
